{
  "title": "Seoul Youth Basic Ordinance",
  "version": "normalized-2023-07-24-revision",
  "clauses": [
    {
      "id": "c1",
      "title": "Eligibility Age Requirement",
      "text": "청년은 서울특별시에 거주하는 만 19세 이상 39세 이하의 사람으로 본다."
    },
    {
      "id": "c2",
      "title": "Required Documents for Survey",
      "text": "시장은 청년정책 기본계획 수립을 위해 실태조사 자료, 부서 제출 자료, 정책 참여 결과보고서를 요구할 수 있다."
    },
    {
      "id": "c3",
      "title": "Plan Publication Deadline",
      "text": "연도별 청년정책 시행계획은 매년 4월 30일까지 공표한다."
    },
    {
      "id": "c4",
      "title": "Support Amount Standard",
      "text": "청년사업 지원금 기준은 시행계획과 성과평가 결과를 반영한다."
    }
  ]
}
